downy/__init__.py
downy/download.py
downy-0.1.1.dist-info/AUTHORS
downy-0.1.1.dist-info/COPYING
downy-0.1.1.dist-info/METADATA
downy-0.1.1.dist-info/WHEEL
downy-0.1.1.dist-info/entry_points.txt
downy-0.1.1.dist-info/top_level.txt
downy-0.1.1.dist-info/RECORD
