Metadata-Version: 2.1
Name: downy
Version: 0.1.1
Summary: Python package for Downloading Files in a blink of the eye
Home-page: https://shreyasb.com/
Author: Shreyas Bapat
Author-email: contact@shreyasb.com
License: MIT
Download-URL: https://github.com/downy/downy
Keywords: download,threads,idm,download manager,fast
Platform: UNKNOWN
Classifier: Development Status :: 4 - Beta
Classifier: Intended Audience :: Education
Classifier: License :: OSI Approved :: MIT License
Classifier: Operating System :: OS Independent
Classifier: Programming Language :: Python
Classifier: Programming Language :: Python :: 3
Classifier: Programming Language :: Python :: 3.5
Classifier: Programming Language :: Python :: 3.6
Requires-Python: >=3.5
Requires-Dist: requests
Requires-Dist: psutil
Provides-Extra: dev
Requires-Dist: coverage ; extra == 'dev'
Requires-Dist: pytest-cov ; extra == 'dev'
Requires-Dist: pycodestyle ; extra == 'dev'
Requires-Dist: sphinx ; extra == 'dev'
Requires-Dist: alabaster ; extra == 'dev'
Requires-Dist: nbsphinx ; extra == 'dev'
Requires-Dist: ipython (>=5.0) ; extra == 'dev'
Requires-Dist: jupyter-client ; extra == 'dev'
Requires-Dist: ipykernel ; extra == 'dev'
Requires-Dist: ipywidgets ; extra == 'dev'
